cnab/__init__.py
cnab/banks/__init__.py
cnab/banks/banco_brasil/__init__.py
cnab/banks/banco_brasil/CNAB240/__init__.py
cnab/banks/banco_brasil/CNAB240/remessa/__init__.py
cnab/banks/banco_brasil/CNAB240/remessa/registro0.py
cnab/banks/banco_brasil/CNAB240/remessa/registro1.py
cnab/banks/banco_brasil/CNAB240/remessa/registro3P.py
cnab/banks/banco_brasil/CNAB240/remessa/registro3Q.py
cnab/banks/banco_brasil/CNAB240/remessa/registro3R.py
cnab/banks/banco_brasil/CNAB240/remessa/registro3S1e2.py
cnab/banks/banco_brasil/CNAB240/remessa/registro3S3.py
cnab/banks/banco_brasil/CNAB240/remessa/registro5.py
cnab/banks/banco_brasil/CNAB240/remessa/registro9.py
cnab/banks/banco_brasil/CNAB240/remessa/remessa.py
cnab/banks/bradesco/__init__.py
cnab/banks/bradesco/CNAB400/__init__.py
cnab/banks/bradesco/CNAB400/remessa/__init__.py
cnab/banks/bradesco/CNAB400/remessa/registro0.py
cnab/banks/bradesco/CNAB400/remessa/registro1.py
cnab/banks/bradesco/CNAB400/remessa/registro2.py
cnab/banks/bradesco/CNAB400/remessa/registro9.py
cnab/banks/bradesco/CNAB400/remessa/remessa.py
cnab/banks/bradesco/CNAB400/retorno/__init__.py
cnab/banks/bradesco/CNAB400/retorno/registro0.py
cnab/banks/bradesco/CNAB400/retorno/registro1.py
cnab/banks/bradesco/CNAB400/retorno/registro4.py
cnab/banks/bradesco/CNAB400/retorno/registro9.py
cnab/banks/bradesco/CNAB400/retorno/retorno.py
cnab/banks/caixa/__init__.py
cnab/banks/caixa/CNAB240/__init__.py
cnab/banks/caixa/CNAB240/remessa/__init__.py
cnab/banks/caixa/CNAB240/remessa/registro0.py
cnab/banks/caixa/CNAB240/remessa/registro1.py
cnab/banks/caixa/CNAB240/remessa/registro3P.py
cnab/banks/caixa/CNAB240/remessa/registro3Q.py
cnab/banks/caixa/CNAB240/remessa/registro3R.py
cnab/banks/caixa/CNAB240/remessa/registro3S1e2.py
cnab/banks/caixa/CNAB240/remessa/registro3S3.py
cnab/banks/caixa/CNAB240/remessa/registro5.py
cnab/banks/caixa/CNAB240/remessa/registro9.py
cnab/banks/caixa/CNAB240/remessa/remessa.py
cnab/banks/caixa/CNAB240/retorno/__init__.py
enhanced_cnab-0.0.19.dist-info/METADATA
enhanced_cnab-0.0.19.dist-info/WHEEL
enhanced_cnab-0.0.19.dist-info/top_level.txt
enhanced_cnab-0.0.19.dist-info/RECORD
