Metadata-Version: 2.1
Name: enhanced-cnab
Version: 0.0.19
Summary: Enhanced way to generate brazil banks CNAB files in python.
Home-page: https://github.com/EduardoJM/enhanced-cnab
Author: Eduardo Oliveira
Author-email: eduardo_y05@outlook.com
License: MIT
Keywords: cnab,banks,boletos,remessa,lote,cnab240,cnab400
Classifier: Development Status :: 5 - Production/Stable
Classifier: Environment :: Web Environment
Classifier: Intended Audience :: Developers
Classifier: License :: OSI Approved :: MIT License
Classifier: Operating System :: OS Independent
Classifier: Programming Language :: Python
Classifier: Programming Language :: Python :: 3
Classifier: Programming Language :: Python :: 3.8
Classifier: Programming Language :: Python :: 3.9
Classifier: Programming Language :: Python :: 3.10
Classifier: Programming Language :: Python :: 3.11
Classifier: Programming Language :: Python :: 3.12
Requires-Dist: Babel
Requires-Dist: Unidecode
